flaskerror/__init__.py
flaskerror/config.py
flaskerror/core.py
test/__init__.py
test/conftest.py
test/test_error.py
FlaskError-1.0.0.dist-info/LICENSE
FlaskError-1.0.0.dist-info/METADATA
FlaskError-1.0.0.dist-info/WHEEL
FlaskError-1.0.0.dist-info/top_level.txt
FlaskError-1.0.0.dist-info/RECORD
